mineru_local_mcp/__init__.py
mineru_local_mcp/client.py
mineru_local_mcp/servers.py
mineru_local_mcp-0.1.0.dist-info/METADATA
mineru_local_mcp-0.1.0.dist-info/WHEEL
mineru_local_mcp-0.1.0.dist-info/entry_points.txt
mineru_local_mcp-0.1.0.dist-info/licenses/LICENSE
mineru_local_mcp-0.1.0.dist-info/RECORD
