Metadata-Version: 2.4
Name: mineru-local-mcp
Version: 0.1.0
Summary: User your local device to run mineru for LLMs.
Project-URL: Source, https://github.com/sepinetam/mineru-local-mcp
Author-email: SongTan <sepinetam@gmail.com>
License-File: LICENSE
Requires-Python: >=3.11
Requires-Dist: mcp[cli]>=1.25.0
Requires-Dist: mineru[all]>=2.7.1
